treels/__init__.py
treels/main.py
treels_cli-1.1.1.dist-info/licenses/LICENSE
treels_cli-1.1.1.dist-info/METADATA
treels_cli-1.1.1.dist-info/WHEEL
treels_cli-1.1.1.dist-info/entry_points.txt
treels_cli-1.1.1.dist-info/top_level.txt
treels_cli-1.1.1.dist-info/RECORD
