Metadata-Version: 2.4
Name: treels-cli
Version: 1.1.1
Summary: Enhanced directory tree printer with Git integration
Author: Faizan Ali
License-Expression: MIT
Requires-Python: >=3.8
License-File: LICENSE
Requires-Dist: rich>=13.0.0
Dynamic: license-file
